code_mintage/__init__.py
code_mintage/cpp_properties.py
code_mintage/default_settings.json
code_mintage/jlink_scripts.py
code_mintage/main.py
code_mintage/project_tree.py
code_mintage/settings.py
code_mintage/tasks.py
code_mintage/version.py
code_mintage-0.1.0.dist-info/LICENSE
code_mintage-0.1.0.dist-info/METADATA
code_mintage-0.1.0.dist-info/WHEEL
code_mintage-0.1.0.dist-info/entry_points.txt
code_mintage-0.1.0.dist-info/top_level.txt
code_mintage-0.1.0.dist-info/RECORD
