Metadata-Version: 2.1
Name: code-mintage
Version: 0.1.0
Summary: Creating VScode config for the Embedded Project.
Home-page: https://github.com/Mcublog/code-mintage
Author: Viacheslav
Author-email: viacheslav@mcublog.ru
Classifier: Programming Language :: Python :: 3
Classifier: License :: OSI Approved :: MIT License
Classifier: Operating System :: OS Independent
Requires-Python: >=3.8
License-File: LICENSE
Requires-Dist: colorama (==0.4.4)
